musicians_choice_lib_pkg/__init__.py
musicians_choice_lib_pkg/musicians_choice_lib.py
musicians_choice_cpp_lib-0.0.1.dist-info/LICENSE
musicians_choice_cpp_lib-0.0.1.dist-info/METADATA
musicians_choice_cpp_lib-0.0.1.dist-info/WHEEL
musicians_choice_cpp_lib-0.0.1.dist-info/top_level.txt
musicians_choice_cpp_lib-0.0.1.dist-info/RECORD
