Metadata-Version: 2.1
Name: musicians-choice-cpp-lib
Version: 0.0.1
Summary: Custom library for CPP project
Home-page: https://github.com/pypa/sampleproject
Author: David Tynan
Author-email: x20153104@student.ncirl.ie
License: UNKNOWN
Platform: UNKNOWN
Classifier: Programming Language :: Python :: 3
Classifier: License :: OSI Approved :: MIT License
Classifier: Operating System :: OS Independent
Requires-Python: >=3.6
License-File: LICENSE
